Metadata-Version: 2.1
Name: compressed-spreadsheets
Version: 1.0.0
Summary: Read & write to gzip compressed CSV files.
Home-page: https://github.com/MaxBondABE/compressed_spreadsheets
Author: Max Bond
License: UNKNOWN
Keywords: compressed,csv
Platform: UNKNOWN
Requires-Python: >=3.5, <4
